{
  "version": "1.1.1",
  "windows": {
    "main": {
      "main": true,
      "url": "app://editor/index.html",
      "windowType": "dockable",
      "x": 196,
      "y": 82,
      "width": 2079,
      "height": 1222,
      "layout": {
        "children": [
          {
            "children": [
              {
                "active": 0,
                "children": [
                  "hierarchy"
                ],
                "height": 540.234375,
                "type": "panel",
                "width": 388
              },
              {
                "active": 0,
                "children": [
                  "assets",
                  "cloud-function"
                ],
                "height": 589.265625,
                "type": "panel",
                "width": 388
              }
            ],
            "height": 1132.5,
            "type": "dock-v",
            "width": 388
          },
          {
            "active": 0,
            "children": [
              "inspector",
              "cocos-services"
            ],
            "height": 1132.5,
            "type": "panel",
            "width": 431
          },
          {
            "children": [
              {
                "active": 0,
                "children": [
                  "scene"
                ],
                "height": 862.625,
                "type": "panel",
                "width": 1253.984375
              },
              {
                "active": 0,
                "children": [
                  "console",
                  "timeline",
                  "game-window",
                  "quick-open-x"
                ],
                "height": 266.875,
                "type": "panel",
                "width": 1253.984375
              }
            ],
            "height": 1132.5,
            "type": "dock-v",
            "width": 1253.984375
          }
        ],
        "type": "dock-h"
      },
      "panels": [
        "hierarchy",
        "assets",
        "cloud-function",
        "inspector",
        "cocos-services",
        "scene",
        "console",
        "timeline",
        "game-window",
        "quick-open-x"
      ]
    },
    "worker": {}
  },
  "panels": {
    "sprite-editor": {
      "x": 1001,
      "y": 443,
      "width": 500,
      "height": 528
    },
    "quick-open-x": {
      "x": 850,
      "y": 393,
      "width": 800,
      "height": 628
    }
  },
  "panelLabelWidth": {
    "inspector": null
  }
}
